.gitignore
LICENSE
README.md
pyproject.toml
uv.lock
.github/workflows/docs.yml
.github/workflows/release.yml
.github/workflows/test.yaml
docs/source/conf.py
docs/source/index.rst
ommx_fixstars_amplify_adapter/__init__.py
ommx_fixstars_amplify_adapter/_version.py
ommx_fixstars_amplify_adapter/adapter.py
ommx_fixstars_amplify_adapter/amplify_to_ommx.py
ommx_fixstars_amplify_adapter/exception.py
ommx_fixstars_amplify_adapter.egg-info/PKG-INFO
ommx_fixstars_amplify_adapter.egg-info/SOURCES.txt
ommx_fixstars_amplify_adapter.egg-info/dependency_links.txt
ommx_fixstars_amplify_adapter.egg-info/requires.txt
ommx_fixstars_amplify_adapter.egg-info/top_level.txt
tests/conftest.py
tests/test_amplify.py
tests/test_instance_to_model.py
tests/test_model_to_instance.py