Metadata-Version: 2.4
Name: ommx_fixstars_amplify_adapter
Version: 0.3.1
Summary: An adapter for the Fixstars Amplify from/to OMMX.
Author-email: "Jij Inc." <info@j-ij.com>
Classifier: Programming Language :: Python :: 3 :: Only
Classifier: Programming Language :: Python :: 3.8
Classifier: Programming Language :: Python :: 3.9
Classifier: Programming Language :: Python :: 3.10
Classifier: Programming Language :: Python :: 3.11
Classifier: Programming Language :: Python :: 3.12
Classifier: License :: OSI Approved :: Apache Software License
Requires-Python: >=3.9
License-File: LICENSE
Requires-Dist: ommx<3.0.0,>=2.0.3
Requires-Dist: amplify<2.0.0,>=1.2.0
Provides-Extra: dev
Requires-Dist: pyright; extra == "dev"
Requires-Dist: pytest; extra == "dev"
Requires-Dist: ruff; extra == "dev"
Requires-Dist: sphinx; extra == "dev"
Requires-Dist: sphinx-autoapi; extra == "dev"
Requires-Dist: sphinx_fontawesome; extra == "dev"
Requires-Dist: sphinx_rtd_theme; extra == "dev"
Dynamic: license-file
